<?xml version="1.0" encoding="utf-8"?>
<Application>
  <Views Id="Views">
    <DetailView Id="ExcelImport_DetailView">
      <Layout Id="Layout">
        <LayoutGroup Id="Main">
          <LayoutGroup Id="SimpleEditors">
            <LayoutGroup Id="Auto00224b34-7006-4108-b0c5-3487562c098d" RelativeSize="49.133858267716533" />
            <LayoutGroup Id="Autoe95d7ad6-b37f-40c5-bc50-cf78c6c8acaf" RelativeSize="50.866141732283467">
              <LayoutItem Id="Type" RelativeSize="17.910447761194028" Index="1" ViewItem="Type" />
            </LayoutGroup>
          </LayoutGroup>
        </LayoutGroup>
      </Layout>
    </DetailView>
  </Views>
</Application>